MANIFEST.in
README
README.rst
setup.py
activation/__init__.py
activation/models.py
activation/signals.py
activation/tests.py
activation/management/__init__.py
django_activation.egg-info/PKG-INFO
django_activation.egg-info/SOURCES.txt
django_activation.egg-info/dependency_links.txt
django_activation.egg-info/requires.txt
django_activation.egg-info/top_level.txt
example/__init__.py
example/manage.py
example/settings.py
example/urls.py
example/app/__init__.py
example/app/models.py
example/app/tests.py