Metadata-Version: 1.0
Name: django-activation
Version: 0.1.2
Summary: Simple activation of users.
Home-page: UNKNOWN
Author: Jorge Eduardo Cardona Gaviria
Author-email: jorgeecardona@gmail.com
License: BSD
Platform: UNKNOWN
